<?xml version="1.0"?>
<?xml-stylesheet type="text/xsl" href="../css/strict.xsl"?>
<PAGE xmlns:xsi="http://www.w3.org/2001/XMLSchema-instance" xsi:noNamespaceSchemaLocation="../css/schema.xsd" xml:lang="en">
<TITLE>Humour</TITLE>
<PATH>links/humor.xml</PATH>
<DATE><YEAR>2023</YEAR><MONTH>2</MONTH><DAY>4</DAY></DATE>
<CONTENT>
<LLIST>
  <ITEM><SLIST>
    <ITEM><CLIST><TITLE>Defakator</TITLE>
      <ITEM><X><T>YouTube</T><A>https://www.youtube.com/channel/UCU0FhLr6fr7U9GOn6OiQHpQ</A><L>fr</L><F>HTML</F><FEED><A>https://www.youtube.com/feeds/videos.xml?channel_id=UCU0FhLr6fr7U9GOn6OiQHpQ</A><F>RSS</F></FEED></X></ITEM>
      <ITEM><X><T>Twitter</T><A>https://twitter.com/DEFAKATOR_Off</A><L>fr</L><F>HTML</F></X></ITEM>
    </CLIST></ITEM>
    <ITEM><CLIST><TITLE>Films</TITLE>
      <ITEM><X><T>Happy Tree Friends</T><A>https://mondomedia.com/</A><L>en</L><F>HTML</F></X></ITEM>
    </CLIST></ITEM>
    <ITEM><X><T>Despair, Inc.</T><A>https://despair.com/</A><L>en</L><F>HTML</F></X></ITEM>
    <ITEM><BLIST><TITLE>Nerd humor</TITLE>
      <ITEM><X><T>The International Obfuscated C Code Contest</T><A>https://www.ioccc.org/index.html</A><L>en</L><F>HTML</F></X></ITEM>
      <ITEM><X><T>The Quine Page</T><A>http://www.nyx.net/%7Egthompso/quine.htm</A><L>en</L><F>HTML</F></X></ITEM>
      <ITEM><X><T>The Easter Egg Archive</T><A>https://eeggs.com/</A><L>en</L><F>HTML</F></X></ITEM>
      <ITEM><X status="obsolete"><T>Software Wars</T><A>https://www.atai.org/softwarewar.png</A><L>en</L><F>HTML</F></X></ITEM>
      <ITEM><X status="obsolete"><T>The Mozilla Museum</T><A>http://home.snafu.de/tilman/mozilla/</A><L>en</L><F>HTML</F></X></ITEM>
      <ITEM><X status="obsolete"><T>Kasskoyee</T><A>https://www.kasskooye.com/</A><L>fr</L><F>HTML</F></X></ITEM>
      <ITEM><X><T>Python</T><A>https://www.python.org/doc/humor/</A><L>en</L><F>HTML</F></X></ITEM>
      <ITEM><X><T>The Shakespeare Programming Language</T><A>https://shakespearelang.com/</A><L>en</L><F>HTML</F></X></ITEM>
      <ITEM><CLIST><TITLE><X><T>xkcd</T><A>https://xkcd.com</A><L>en</L><F>HTML</F><FEED><A>https://xkcd.com/atom.xml</A><F>Atom</F></FEED></X></TITLE>
        <ITEM><X><T>explain xkcd</T><A>https://www.explainxkcd.com/wiki/index.php/Main_Page</A><L>en</L><F>HTML</F></X></ITEM>
        <ITEM><X><T>what if?</T><A>https://what-if.xkcd.com</A><L>en</L><F>HTML</F><FEED><A>https://what-if.xkcd.com/feed.atom</A><F>Atom</F></FEED></X></ITEM>
      </CLIST></ITEM>
      <ITEM><X><T>Dilbert</T><A>https://dilbert.com</A><L>en</L><F>HTML</F></X></ITEM>
    </BLIST></ITEM>
    <ITEM><BLIST><TITLE>Facts</TITLE>
      <ITEM><X><T>Bruce Schneier</T><A>https://www.schneierfacts.com</A><L>en</L><F>HTML</F></X></ITEM>
      <ITEM><X><T>Jon Skeet</T><A>https://meta.stackexchange.com/questions/9134/jon-skeet-facts</A><L>en</L><F>HTML</F></X></ITEM>
    </BLIST></ITEM>
    <ITEM><CLIST><TITLE>Comics</TITLE>
      <ITEM><X><T>user friendly</T><A>http://www.userfriendly.org/</A><L>en</L><F>HTML</F></X></ITEM>
    </CLIST></ITEM>
    <ITEM><BLIST><TITLE>Reality and legends</TITLE>
      <ITEM><X><T>Darwin awards</T><A>https://darwinawards.com/</A><L>en</L><F>HTML</F></X></ITEM>
      <ITEM><X><T>news of the weird</T><A>https://www.uexpress.com/oddities/news-of-the-weird</A><L>en</L><F>HTML</F></X></ITEM>
    </BLIST></ITEM>
    <ITEM><X><T>the chicken gun</T><A>http://strangeplaces.net/weirdthings/chickengun.html</A><L>en</L><F>HTML</F></X></ITEM>
    <ITEM><X><T>the potato gun</T><A>http://www.claytonbailey.com/potatogun.htm</A><L>en</L><F>HTML</F></X></ITEM>
    <ITEM><X><T>Ze Jacky Touch / 100% Jacky Tuning</T><A>http://www.zejackytouch.com</A><L>fr</L><F>HTML</F></X></ITEM>
    <ITEM><X><T>Donjon de Naheulbeuk</T><A>http://www.penofchaos.com/warham/donjon.htm</A><L>fr</L><F>HTML</F></X></ITEM>
  </SLIST></ITEM>
  <ITEM><BLIST><TITLE>Articles and videos</TITLE>
    <ITEM><ARTICLE><X><T>Cannot find Weapons of Mass Destruction</T><A>https://blueguitar.net/new/misc/humor/wmd_spoof.pdf</A><L>en</L><F>PDF</F></X><COMMENT>A new version of the 404 error message.</COMMENT></ARTICLE></ITEM>
    <ITEM><ARTICLE><X status="zombie"><T>Cement Teddy Bears</T><A>https://www.cultdeadcow.com/cDc_files/cDc-0368.txt</A><L>en</L><F>txt</F></X><AUTHOR><GIVENNAME>Rev. Al</GIVENNAME></AUTHOR><DATE><YEAR>1999</YEAR><MONTH>6</MONTH><DAY>6</DAY></DATE><COMMENT>When a Teddy Bear is stuffed with cement and drops on your foot.</COMMENT></ARTICLE></ITEM>
    <ITEM><ARTICLE><X><T>Postal Experiments</T><A>https://improbable.com/airchives/paperair/volume6/v6i4/postal-6-4.php</A><L>en</L><F>HTML</F></X><AUTHOR><FIRSTNAME>Jeff</FIRSTNAME><LASTNAME>van Bueren</LASTNAME></AUTHOR><DATE><YEAR>2000</YEAR></DATE><COMMENT>Some testing of the US Postal Service.</COMMENT></ARTICLE></ITEM>
    <ITEM><ARTICLE><X quality="1"><T>How to sound smart in your TEDx Talk | Will Stephen | TEDxNewYork</T><A>https://www.youtube.com/watch?v=8S0FDjFBj8o</A><L>en</L><F>MP4</F><DURATION><MINUTE>5</MINUTE><SECOND>55</SECOND></DURATION></X><AUTHOR><FIRSTNAME>Will</FIRSTNAME><LASTNAME>Stephen</LASTNAME></AUTHOR><DATE><YEAR>2015</YEAR><MONTH>1</MONTH><DAY>15</DAY></DATE><COMMENT>A good satire of TED-style presentations.</COMMENT></ARTICLE></ITEM>
    <ITEM><ARTICLE><X quality="1"><T>‘Thought Leader’ gives talk that will inspire your thoughts | CBC Radio (Comedy/Satire Skit)</T><A>https://www.youtube.com/watch?v=_ZBKX-6Gz6A</A><L>en</L><F>MP4</F><DURATION><MINUTE>4</MINUTE><SECOND>15</SECOND></DURATION></X><DATE><YEAR>2016</YEAR><MONTH>6</MONTH><DAY>8</DAY></DATE><COMMENT>The same.</COMMENT></ARTICLE></ITEM>
    <ITEM><ARTICLE><X><T>Ma chaine a 5 ans ! ... et si je changeais de style ?</T><A>https://www.youtube.com/watch?v=2A5eUEHXO8Q</A><L>fr</L><F>MP4</F><DURATION><MINUTE>11</MINUTE><SECOND>37</SECOND></DURATION></X><AUTHOR><GIVENNAME>Professeur Culture Précieuse</GIVENNAME></AUTHOR><DATE><YEAR>2019</YEAR><MONTH>8</MONTH><DAY>14</DAY></DATE><COMMENT>Some imitations of French science popularisers.</COMMENT></ARTICLE></ITEM>
    <ITEM><ARTICLE><X><T>Why do people keep getting this wrong‽</T><A>https://www.youtube.com/watch?v=6egeUxIEQnM</A><L>en</L><F>MP4</F><DURATION><MINUTE>12</MINUTE><SECOND>48</SECOND></DURATION></X><AUTHOR><FIRSTNAME>Matt</FIRSTNAME><LASTNAME>Parker</LASTNAME></AUTHOR><DATE><YEAR>2020</YEAR><MONTH>3</MONTH><DAY>24</DAY></DATE><COMMENT>When people fail to divide millions.</COMMENT></ARTICLE></ITEM>
    <ITEM><ARTICLE><X><T>Dad Photoshops Kids’ Drawings As If They Were Real, And It’s Terrifyingly Funny</T><ST>Interview With Artist</ST><A>https://www.boredpanda.com/drawings-real-life-things-i-have-drawn/</A><L>en</L><F>HTML</F></X><AUTHOR><FIRSTNAME>Jonas</FIRSTNAME><LASTNAME>Grinevičius</LASTNAME></AUTHOR><AUTHOR><FIRSTNAME>Greta</FIRSTNAME><LASTNAME>Jaruševičiūtė</LASTNAME></AUTHOR><DATE><YEAR>2020</YEAR><MONTH>7</MONTH><DAY>22</DAY></DATE><COMMENT><AUTHOR><FIRSTNAME>Tom</FIRSTNAME><LASTNAME>Curtis</LASTNAME></AUTHOR> creates photoshopped images based on the drawings of his children.</COMMENT></ARTICLE></ITEM>
    <ITEM><ARTICLE><X><T>Google Maps Adds Shortcuts Through Houses Of People Google Knows Aren’t Home Right Now</T><A>https://www.theonion.com/google-maps-adds-shortcuts-through-houses-of-people-goo-1848861825</A><L>en</L><F>HTML</F></X><DATE><YEAR>2022</YEAR><MONTH>5</MONTH><DAY>12</DAY></DATE><COMMENT>The title says is all.</COMMENT></ARTICLE></ITEM>
    <ITEM><ARTICLE><X><T>Quand l’humour s’invite dans les articles médicaux</T><A>https://www.lemonde.fr/blog/realitesbiomedicales/2023/01/03/quand-lhumour-sinvite-dans-les-articles-medicaux/</A><L>fr</L><F>HTML</F></X><AUTHOR><FIRSTNAME>Marc</FIRSTNAME><LASTNAME>Gozlan</LASTNAME></AUTHOR><DATE><YEAR>2023</YEAR><MONTH>1</MONTH><DAY>3</DAY></DATE><COMMENT>Some (moderately) funny titles of medical papers.</COMMENT></ARTICLE></ITEM>
    <ITEM><ARTICLE predecessor="https://www.lemonde.fr/blog/realitesbiomedicales/2023/01/03/quand-lhumour-sinvite-dans-les-articles-medicaux/"><X><T>Ces titres improbables de publications scientifiques en biologie</T><A>https://www.lemonde.fr/blog/realitesbiomedicales/2023/01/18/ces-titres-improbables-de-publications-scientifiques-en-biologie/</A><L>fr</L><F>HTML</F></X><AUTHOR><FIRSTNAME>Marc</FIRSTNAME><LASTNAME>Gozlan</LASTNAME></AUTHOR><DATE><YEAR>2023</YEAR><MONTH>1</MONTH><DAY>18</DAY></DATE><COMMENT>The same with some names of genes, plants, or animals.</COMMENT></ARTICLE></ITEM>
    <ITEM><ARTICLE><X><T>États-Unis : un chien déclenche une arme à feu et tue un chasseur. Un précédent documenté en 2001</T><A>https://www.lemonde.fr/blog/realitesbiomedicales/2023/01/25/etats-unis-un-chien-declenche-une-arme-a-feu-et-tue-un-chasseur/</A><L>fr</L><F>HTML</F></X><AUTHOR><FIRSTNAME>Marc</FIRSTNAME><LASTNAME>Gozlan</LASTNAME></AUTHOR><DATE><YEAR>2023</YEAR><MONTH>1</MONTH><DAY>25</DAY></DATE><COMMENT>No comment…</COMMENT></ARTICLE></ITEM>
    <ITEM><BLIST><TITLE>Debunking</TITLE>
      <ITEM><ARTICLE><X><T>Homéopathie : 200 ans d'histoire, quel avenir ?</T><A>https://www.youtube.com/watch?v=8EVWnMFF5zI</A><L>fr</L><F>MP4</F><DURATION><HOUR>1</HOUR><MINUTE>35</MINUTE><SECOND>4</SECOND></DURATION></X><AUTHOR><FIRSTNAME>Jean-Paul</FIRSTNAME><LASTNAME>Krivine</LASTNAME></AUTHOR><DATE><YEAR>2020</YEAR><MONTH>11</MONTH><DAY>28</DAY></DATE><COMMENT>The usual explanations of why homeopathy is bullshit.</COMMENT></ARTICLE></ITEM>
      <ITEM><BLIST><TITLE>Defakator</TITLE>
        <ITEM><ARTICLE><X><T>🌠 La téléportation - DEFAKATOR</T><A>https://www.youtube.com/watch?v=e1XjsOny1Pk</A><L>fr</L><F>MP4</F><DURATION><MINUTE>5</MINUTE><SECOND>57</SECOND></DURATION></X><AUTHOR><GIVENNAME>Defakator</GIVENNAME></AUTHOR><DATE><YEAR>2016</YEAR><MONTH>11</MONTH><DAY>28</DAY></DATE><COMMENT>The title says it all.</COMMENT></ARTICLE></ITEM>
        <ITEM><ARTICLE><X status="zombie"><T>📡 Les satellites n'existent pas</T><A>https://www.youtube.com/watch?v=B00LDAAkQPg</A><L>fr</L><F>MP4</F><DURATION><MINUTE>5</MINUTE><SECOND>24</SECOND></DURATION></X><AUTHOR><GIVENNAME>Defakator</GIVENNAME></AUTHOR><DATE><YEAR>2016</YEAR><MONTH>12</MONTH><DAY>6</DAY></DATE><COMMENT>The title says it all.</COMMENT></ARTICLE></ITEM>
        <ITEM><ARTICLE><X><T>🔌 De l'électricité gratuite avec l'énergie libre - DEFAKATOR</T><A>https://www.youtube.com/watch?v=k5O73SY47LI</A><L>fr</L><F>MP4</F><DURATION><MINUTE>49</MINUTE><SECOND>37</SECOND></DURATION></X><AUTHOR><GIVENNAME>Defakator</GIVENNAME></AUTHOR><DATE><YEAR>2017</YEAR><MONTH>4</MONTH><DAY>17</DAY></DATE><COMMENT>How to generate free energy.</COMMENT></ARTICLE></ITEM>
        <ITEM><ARTICLE><X><T>💩 Des gens trafiquent nos souvenirs - DEFAKATOR</T><A>https://www.youtube.com/watch?v=dDEPald8oDM</A><L>fr</L><F>MP4</F><DURATION><MINUTE>45</MINUTE><SECOND>27</SECOND></DURATION></X><AUTHOR><GIVENNAME>Defakator</GIVENNAME></AUTHOR><DATE><YEAR>2017</YEAR><MONTH>5</MONTH><DAY>17</DAY></DATE><COMMENT>Mandela effect.</COMMENT></ARTICLE></ITEM>
        <ITEM><ARTICLE><X><T>👻 Les vidéos qui font peur - DEFAKATOR</T><A>https://www.youtube.com/watch?v=nzKxVB1gKnA</A><L>fr</L><F>MP4</F><DURATION><MINUTE>33</MINUTE><SECOND>36</SECOND></DURATION></X><AUTHOR><GIVENNAME>Defakator</GIVENNAME></AUTHOR><DATE><YEAR>2017</YEAR><MONTH>8</MONTH><DAY>6</DAY></DATE><COMMENT>Horror videos.</COMMENT></ARTICLE></ITEM>
        <ITEM><ARTICLE><X><T>🌙 On n'a pas dansé sur la Lune - DEFAKATOR</T><A>https://www.youtube.com/watch?v=BrEtgFHVvkY</A><L>fr</L><F>MP4</F><DURATION><MINUTE>59</MINUTE><SECOND>25</SECOND></DURATION></X><AUTHOR><GIVENNAME>Defakator</GIVENNAME></AUTHOR><DATE><YEAR>2017</YEAR><MONTH>9</MONTH><DAY>5</DAY></DATE><COMMENT>Nobody has ever been on the moon.</COMMENT></ARTICLE></ITEM>
        <ITEM><ARTICLE><X><T>🎭 On nous fake profond - DEFAKATOR</T><A>https://www.youtube.com/watch?v=AT89_nM0nes</A><L>fr</L><F>MP4</F><DURATION><MINUTE>55</MINUTE><SECOND>20</SECOND></DURATION></X><AUTHOR><GIVENNAME>Defakator</GIVENNAME></AUTHOR><DATE><YEAR>2019</YEAR><MONTH>4</MONTH><DAY>23</DAY></DATE><COMMENT>How to detect deepfakes.</COMMENT></ARTICLE></ITEM>
        <ITEM><ARTICLE><X><T>📈 TUTO : Détecter des graphiques trompeurs – DEFAKATOR</T><A>https://www.youtube.com/watch?v=crTt-QIyS-o</A><L>fr</L><F>MP4</F><DURATION><MINUTE>29</MINUTE><SECOND>14</SECOND></DURATION></X><AUTHOR><GIVENNAME>Defakator</GIVENNAME></AUTHOR><DATE><YEAR>2019</YEAR><MONTH>5</MONTH><DAY>22</DAY></DATE><COMMENT>"Errors" in charts/graphs.</COMMENT></ARTICLE></ITEM>
        <ITEM><ARTICLE><X><T>🧆 VITE FAIT : La science sans preuves</T><A>https://www.youtube.com/watch?v=w72CQAlo4CU</A><L>fr</L><F>MP4</F><DURATION><MINUTE>5</MINUTE><SECOND>10</SECOND></DURATION></X><AUTHOR><GIVENNAME>Defakator</GIVENNAME></AUTHOR><DATE><YEAR>2020</YEAR><MONTH>6</MONTH><DAY>18</DAY></DATE><COMMENT>The story of <AUTHOR><FIRSTNAME>Prosper-René</FIRSTNAME><LASTNAME>Blondlot</LASTNAME></AUTHOR> and the <KEYWORD><KEYID>N rays</KEYID><KEYEDTEXT>N rays</KEYEDTEXT></KEYWORD>.</COMMENT></ARTICLE></ITEM>
        <ITEM><ARTICLE><X><T>🧟 Les gens qui n'existent pas - DEFAKATOR</T><A>https://www.youtube.com/watch?v=BhHeOtF9hM4</A><L>fr</L><F>MP4</F><DURATION><MINUTE>56</MINUTE><SECOND>8</SECOND></DURATION></X><AUTHOR><GIVENNAME>Defakator</GIVENNAME></AUTHOR><DATE><YEAR>2020</YEAR><MONTH>8</MONTH><DAY>3</DAY></DATE><COMMENT>Bots, zombies, trolls, and AI.</COMMENT></ARTICLE></ITEM>
        <ITEM><ARTICLE><X><T>🧆 VITE FAIT : L'astroturfing</T><A>https://www.youtube.com/watch?v=8wU0Cd7p2vo</A><L>fr</L><F>MP4</F><DURATION><MINUTE>5</MINUTE><SECOND>10</SECOND></DURATION></X><AUTHOR><GIVENNAME>Defakator</GIVENNAME></AUTHOR><DATE><YEAR>2020</YEAR><MONTH>8</MONTH><DAY>17</DAY></DATE><COMMENT>A description of astrosurfing.</COMMENT></ARTICLE></ITEM>
        <ITEM><ARTICLE><X><T>🗺️ Voyage au pays des méchants et des gentils - DEFAKATOR</T><A>https://www.youtube.com/watch?v=PqbYXvkmc98</A><L>fr</L><F>MP4</F><DURATION><MINUTE>25</MINUTE><SECOND>42</SECOND></DURATION></X><AUTHOR><GIVENNAME>Defakator</GIVENNAME></AUTHOR><DATE><YEAR>2021</YEAR><MONTH>1</MONTH><DAY>26</DAY></DATE><COMMENT>When we debate with someone else, we must analyse if his/her claims are his/her opinion or if they are just a way to belong to a group.</COMMENT></ARTICLE></ITEM>
        <ITEM><ARTICLE><X><T>🦸‍♂️ TUTO : Prendre de la hauteur</T><A>https://www.youtube.com/watch?v=l0iV4uVQ1Ec</A><L>fr</L><F>MP4</F><DURATION><MINUTE>37</MINUTE><SECOND>9</SECOND></DURATION></X><AUTHOR><GIVENNAME>Defakator</GIVENNAME></AUTHOR><DATE><YEAR>2021</YEAR><MONTH>5</MONTH><DAY>1</DAY></DATE><COMMENT>Vox-pops and video extracts used out of their context.</COMMENT></ARTICLE></ITEM>
        <ITEM><ARTICLE><X><T>🏷️ Ça déballe !  -DEFAKATOR</T><A>https://www.youtube.com/watch?v=BnP9AbA_kBU</A><L>fr</L><F>MP4</F><DURATION><MINUTE>59</MINUTE><SECOND>9</SECOND></DURATION></X><AUTHOR><GIVENNAME>Defakator</GIVENNAME></AUTHOR><DATE><YEAR>2022</YEAR><MONTH>1</MONTH><DAY>1</DAY></DATE><COMMENT>Food labelling.</COMMENT></ARTICLE></ITEM>
        <ITEM><ARTICLE><X><T>🗺️Les cartes trompeuses (TUTO)</T><A>https://www.youtube.com/watch?v=n9pkdWpNRws</A><L>fr</L><F>MP4</F><DURATION><MINUTE>37</MINUTE><SECOND>20</SECOND></DURATION></X><AUTHOR><GIVENNAME>Defakator</GIVENNAME></AUTHOR><DATE><YEAR>2022</YEAR><MONTH>8</MONTH><DAY>22</DAY></DATE><COMMENT>Some information on maps.</COMMENT></ARTICLE></ITEM>
        <ITEM><ARTICLE><X><T>🧆 VITE FAIT : La fenêtre d'Overton</T><A>https://www.youtube.com/watch?v=_Jgbni6UQig</A><L>fr</L><F>MP4</F><DURATION><MINUTE>4</MINUTE><SECOND>53</SECOND></DURATION></X><AUTHOR><GIVENNAME>Defakator</GIVENNAME></AUTHOR><DATE><YEAR>2022</YEAR><MONTH>11</MONTH><DAY>26</DAY></DATE><COMMENT>A description of Overton window.</COMMENT></ARTICLE></ITEM>
        <ITEM><ARTICLE><X><T>🌙 Artemis : on nous repromet la Lune</T><A>https://www.youtube.com/watch?v=ZKhqVny4xSA</A><L>fr</L><F>MP4</F><DURATION><MINUTE>58</MINUTE><SECOND>19</SECOND></DURATION></X><AUTHOR><GIVENNAME>Officiel DEFAKATOR</GIVENNAME></AUTHOR><DATE><YEAR>2023</YEAR><MONTH>1</MONTH><DAY>25</DAY></DATE><COMMENT>A presentation of the Artemis program.</COMMENT></ARTICLE></ITEM>
      </BLIST></ITEM>
      <ITEM><BLIST><TITLE>G Milgram</TITLE>
        <ITEM><ARTICLE><X><T>Le business anti-ondes : ENQUÊTE et CANULAR</T><A>https://www.youtube.com/watch?v=ZQ5UYMvMN7A</A><L>fr</L><F>MP4</F><DURATION><MINUTE>26</MINUTE><SECOND>4</SECOND></DURATION></X><AUTHOR><GIVENNAME>G Milgram</GIVENNAME></AUTHOR><DATE><YEAR>2021</YEAR><MONTH>5</MONTH><DAY>28</DAY></DATE><COMMENT>The title says it all.</COMMENT></ARTICLE></ITEM>
        <ITEM><ARTICLE predecessor="https://www.youtube.com/watch?v=ZQ5UYMvMN7A"><X><T>Bio-compensateur géodésique : on me vole mon invention 😌</T><A>https://www.youtube.com/watch?v=JYJjU4NoE4U</A><L>fr</L><F>MP4</F><DURATION><MINUTE>22</MINUTE><SECOND>18</SECOND></DURATION></X><AUTHOR><GIVENNAME>G Milgram</GIVENNAME></AUTHOR><DATE><YEAR>2022</YEAR><MONTH>5</MONTH><DAY>20</DAY></DATE><COMMENT>Some trolls are selling <AUTHOR><GIVENNAME>G Milgram</GIVENNAME></AUTHOR>’s joke.</COMMENT></ARTICLE></ITEM>
        <ITEM><ARTICLE><X><T>L'histoire du bracelet « magique » : Power Balance</T><A>https://www.youtube.com/watch?v=0dVpy6p8uO8</A><L>fr</L><F>MP4</F><DURATION><MINUTE>14</MINUTE><SECOND>24</SECOND></DURATION></X><AUTHOR><GIVENNAME>G Milgram</GIVENNAME></AUTHOR><DATE><YEAR>2022</YEAR><MONTH>9</MONTH><DAY>16</DAY></DATE><COMMENT>The title says it all.</COMMENT></ARTICLE></ITEM>
        <ITEM><ARTICLE><X><T>L'arnaque au Tachyon : ENQUÊTE ‼ (Partie 1)</T><A>https://www.youtube.com/watch?v=-vo3np_yWfw</A><L>fr</L><F>MP4</F><DURATION><MINUTE>25</MINUTE><SECOND>18</SECOND></DURATION></X><AUTHOR><GIVENNAME>G Milgram</GIVENNAME></AUTHOR><DATE><YEAR>2022</YEAR><MONTH>11</MONTH><DAY>9</DAY></DATE><COMMENT>Since there are too many crooks on the quantum healing market, some are building a new bullshit about tachyons.</COMMENT></ARTICLE></ITEM>
        <ITEM><ARTICLE predecessor="https://www.youtube.com/watch?v=-vo3np_yWfw"><X><T>LA SECTE DU TACHYON : j'enquête ! 🕵️‍♂️(Partie 2)</T><A>https://www.youtube.com/watch?v=NtO_UkKWr40</A><L>fr</L><F>MP4</F><DURATION><MINUTE>45</MINUTE><SECOND>44</SECOND></DURATION></X><AUTHOR><GIVENNAME>G Milgram</GIVENNAME></AUTHOR><DATE><YEAR>2022</YEAR><MONTH>11</MONTH><DAY>24</DAY></DATE><COMMENT>It seems that it is easy to trick some poor suckers into buying magic products.</COMMENT></ARTICLE></ITEM>
        <ITEM><ARTICLE predecessor="https://www.youtube.com/watch?v=NtO_UkKWr40"><X><T>Les vendeurs de tachyons me répondent ! (et me censurent)</T><A>https://www.youtube.com/watch?v=QfuyUXDNEHg</A><L>fr</L><F>MP4</F><DURATION><MINUTE>13</MINUTE><SECOND>59</SECOND></DURATION></X><AUTHOR><GIVENNAME>G Milgram</GIVENNAME></AUTHOR><DATE><YEAR>2022</YEAR><MONTH>11</MONTH><DAY>30</DAY></DATE><COMMENT>The crooks are fighting back.</COMMENT></ARTICLE></ITEM>
      </BLIST></ITEM>
      <ITEM><BLIST><TITLE>Captain Disillusion</TITLE>
        <ITEM><ARTICLE><X><T>Escherian Stairwell Deconstruction</T><A>https://www.youtube.com/watch?v=eLAwG7CjF_k</A><L>en</L><F>MP4</F><DURATION><MINUTE>15</MINUTE><SECOND>41</SECOND></DURATION></X><AUTHOR><FIRSTNAME>Alan</FIRSTNAME><LASTNAME>Melikdjanian</LASTNAME></AUTHOR><DATE><YEAR>2018</YEAR><MONTH>8</MONTH><DAY>19</DAY></DATE><COMMENT>Explaining how the Escherian Stairwell was produced.</COMMENT></ARTICLE></ITEM>
      </BLIST></ITEM>
    </BLIST></ITEM>
    <ITEM><BLIST><TITLE>Cartoons</TITLE>
      <ITEM><ARTICLE><X><T>Yes &amp; No: A Dyseducational Road Movie</T><A>https://www.albinoblacksheep.com/flash/yesandno</A><L>en</L><F>Flash</F></X><AUTHOR><FIRSTNAME>Bruno</FIRSTNAME><LASTNAME>Bozzetto</LASTNAME></AUTHOR><DATE><YEAR>2001</YEAR></DATE><COMMENT>Tell me how you drive and I'll tell you what kind of an idiot you are.</COMMENT></ARTICLE></ITEM>
    </BLIST></ITEM>
    <ITEM><BLIST><TITLE>Tu mourras moins bête</TITLE>
      <ITEM><ARTICLE><X><T>SARS-CoV-2 le relou 4000</T><A>http://tumourrasmoinsbete.blogspot.com/2020/05/sars-cov-2-le-relou-4000.html</A><L>fr</L><F>HTML</F></X><AUTHOR><FIRSTNAME>Marion</FIRSTNAME><LASTNAME>Montaigne</LASTNAME></AUTHOR><DATE><YEAR>2020</YEAR><MONTH>5</MONTH><DAY>7</DAY></DATE><COMMENT>A description of viruses.</COMMENT></ARTICLE></ITEM>
      <ITEM><ARTICLE><X><T>Vendredi, SARS_Cov2e partie</T><A>https://tumourrasmoinsbete.blogspot.com/2020/09/vendredi-sarscov2e-partie.html</A><L>fr</L><F>HTML</F></X><AUTHOR><FIRSTNAME>Marion</FIRSTNAME><LASTNAME>Montaigne</LASTNAME></AUTHOR><DATE><YEAR>2020</YEAR><MONTH>9</MONTH><DAY>11</DAY></DATE><COMMENT>Some information about SARS-CoV-2.</COMMENT></ARTICLE></ITEM>
      <ITEM><ARTICLE><X><T>SARS action heros</T><A>https://tumourrasmoinsbete.blogspot.com/2020/10/sars-action-heros.html</A><L>fr</L><F>HTML</F></X><AUTHOR><FIRSTNAME>Marion</FIRSTNAME><LASTNAME>Montaigne</LASTNAME></AUTHOR><DATE><YEAR>2020</YEAR><MONTH>10</MONTH><DAY>20</DAY></DATE><COMMENT>The impact of COVID-19 on the body.</COMMENT></ARTICLE></ITEM>
    </BLIST></ITEM>
    <ITEM><BLIST><TITLE>Nerd humour</TITLE>
      <ITEM><ARTICLE><X><T>A Girl's Guide to Geek Guys</T><A>https://www.neystadt.org/john/humor/Girls-Guide-To-Geek-Guys.htm</A><L>en</L><F>HTML</F></X><AUTHOR><FIRSTNAME>Mikki</FIRSTNAME><LASTNAME>Halpin</LASTNAME></AUTHOR><AUTHOR><FIRSTNAME>Victoria</FIRSTNAME><LASTNAME>Maat</LASTNAME></AUTHOR><DATE><YEAR>1995</YEAR></DATE><COMMENT>Girls just want to have geeks.</COMMENT></ARTICLE></ITEM>
      <ITEM><ARTICLE><X><T>Infrequently Asked Questions in comp.lang.c</T><A>https://www.seebs.net/faqs/c-iaq.html</A><L>en</L><F>HTML</F></X><AUTHOR><FIRSTNAME>Peter</FIRSTNAME><LASTNAME>Seebach</LASTNAME></AUTHOR><DATE><YEAR>1999</YEAR><MONTH>4</MONTH><DAY>16</DAY></DATE><COMMENT>A parody of the FAQ, but some answers have probably been already seen in the newsgroup.</COMMENT></ARTICLE></ITEM>
      <ITEM><ARTICLE><X><T>COFFEE-HOWTO</T><A>http://www.faqs.org/docs/Linux-mini/Coffee.html</A><L>en</L><F>HTML</F></X><AUTHOR><FIRSTNAME>Fotis</FIRSTNAME><LASTNAME>Georgatos</LASTNAME></AUTHOR><AUTHOR><FIRSTNAME>Annie</FIRSTNAME><LASTNAME>Pinder</LASTNAME></AUTHOR><DATE><YEAR>2000</YEAR><MONTH>11</MONTH><DAY>30</DAY></DATE><COMMENT>How to produce coffee with a Linux box.</COMMENT></ARTICLE></ITEM>
      <ITEM><ARTICLE><X><T>Finally, A Solution To The DMCA!</T><A>http://mennucc1.debian.net/Funny/church_of_grepping.html</A><L>en</L><F>HTML</F></X><AUTHOR><FIRSTNAME>James</FIRSTNAME><LASTNAME>Baughn</LASTNAME></AUTHOR><DATE><YEAR>2001</YEAR><MONTH>8</MONTH><DAY>23</DAY></DATE><COMMENT>The title says it all, fight the f*king USA law with their sacrosanct First amendment.</COMMENT></ARTICLE></ITEM>
      <ITEM><ARTICLE><X><T>How Perl Powers Christmas</T><A>https://www.perl.com/pub/2002/12/18/hohoho.html/</A><L>en</L><F>HTML</F></X><AUTHOR><FIRSTNAME>Alex</FIRSTNAME><LASTNAME>Gough</LASTNAME></AUTHOR><DATE><YEAR>2002</YEAR><MONTH>12</MONTH><DAY>18</DAY></DATE><COMMENT>Perl propaganda. It is amazing how much Perl stuff the author has been able to cram in this paper.</COMMENT></ARTICLE></ITEM>
      <ITEM><ARTICLE><X quality="2"><T>Microsoft Re-Designs the iPod Packaging</T><A>https://www.youtube.com/watch?v=EUXnJraKM3k</A><L>en</L><F>MP4</F><DURATION><MINUTE>2</MINUTE><SECOND>55</SECOND></DURATION></X><DATE><YEAR>2006</YEAR><MONTH>2</MONTH><DAY>27</DAY></DATE><COMMENT>What would be the iPod packaging if it would have been designed by Microsoft? This is especially ironic: the video has been created by some Microsoft guys.</COMMENT></ARTICLE></ITEM>
      <ITEM><ARTICLE><X><T>IPhone: The Musical</T><A>https://www.nytimes.com/video/technology/1194817121833/iphone-the-musical.html</A><L>en</L><F>Flash Video</F><DURATION><MINUTE>3</MINUTE><SECOND>17</SECOND></DURATION></X><AUTHOR><FIRSTNAME>David</FIRSTNAME><LASTNAME>Pogue</LASTNAME></AUTHOR><DATE><YEAR>2007</YEAR><MONTH>7</MONTH></DATE><COMMENT>"I did it my way" music reused for the glory of the iPhone.</COMMENT></ARTICLE></ITEM>
      <ITEM><ARTICLE><X><T>Will It Blend? - iPhone</T><A>https://www.youtube.com/watch?v=qg1ckCkm8YI</A><L>en</L><F>MP4</F><DURATION><MINUTE>1</MINUTE><SECOND>37</SECOND></DURATION></X><AUTHOR><GIVENNAME>Blendtec</GIVENNAME></AUTHOR><DATE><YEAR>2007</YEAR><MONTH>7</MONTH><DAY>10</DAY></DATE><COMMENT>Blending an iPhone.</COMMENT></ARTICLE></ITEM>
      <ITEM><ARTICLE><X quality="2"><T>The Expert (Short Comedy Sketch)</T><A>https://www.youtube.com/watch?v=BKorP55Aqvg</A><L>en</L><F>MP4</F><DURATION><MINUTE>7</MINUTE><SECOND>34</SECOND></DURATION></X><DATE><YEAR>2014</YEAR><MONTH>3</MONTH><DAY>23</DAY></DATE><COMMENT>When a consulting firm is asked to draw seven red perpendicular lines using green ink and does not refuse to do it…</COMMENT></ARTICLE></ITEM>
      <ITEM><ARTICLE><X><T>A Collection of O'rly book Covers</T><A>https://boyter.org/2016/04/collection-orly-book-covers/</A><L>en</L><F>HTML</F></X><AUTHOR><FIRSTNAME>Ben</FIRSTNAME><MIDDLENAME>E. C.</MIDDLENAME><LASTNAME>Boyter</LASTNAME></AUTHOR><DATE><YEAR>2016</YEAR><MONTH>4</MONTH><DAY>22</DAY></DATE><COMMENT>O'Reilly book covers.</COMMENT></ARTICLE></ITEM>
      <ITEM><ARTICLE><X><T>Alderson Loop - Computerphile</T><A>https://www.youtube.com/watch?v=Rh1IQwXy3Y8</A><L>en</L><F>MP4</F><DURATION><MINUTE>7</MINUTE><SECOND>15</SECOND></DURATION></X><AUTHOR><FIRSTNAME>Steve</FIRSTNAME><LASTNAME>Bagley</LASTNAME></AUTHOR><DATE><YEAR>2019</YEAR><MONTH>12</MONTH><DAY>21</DAY></DATE><COMMENT>The definition of an Alderson loop: a loop where the exit criteria cannot be met.</COMMENT></ARTICLE></ITEM>
      <ITEM><BLIST><TITLE>Support of dumb users</TITLE>
        <ITEM><ARTICLE><X><T>Befuddled Pc Users Flood Help Lines</T><A>https://www.computerjokes.net/065.asp</A><L>en</L><F>HTML</F></X><DATE><YEAR>1994</YEAR><MONTH>3</MONTH><DAY>1</DAY></DATE><COMMENT>An old article describing some usual hotline jokes.</COMMENT></ARTICLE></ITEM>
        <ITEM><ARTICLE><X><T>10 classic clueless-user stories</T><A>https://www.techrepublic.com/article/10-classic-clueless-user-stories-117197/</A><L>en</L><F>HTML</F></X><DATE><YEAR>2008</YEAR><MONTH>11</MONTH><DAY>25</DAY></DATE><COMMENT>Some other dumb users…</COMMENT></ARTICLE></ITEM>
        <ITEM><ARTICLE><X><T>10 stupid user stories: The madness persists</T><A>https://www.techrepublic.com/article/10-stupid-user-stories-the-madness-persists/</A><L>en</L><F>HTML</F></X><AUTHOR><FIRSTNAME>Brien</FIRSTNAME><LASTNAME>Posey</LASTNAME></AUTHOR><DATE><YEAR>2011</YEAR><MONTH>7</MONTH><DAY>22</DAY></DATE><COMMENT>Some other stories…</COMMENT></ARTICLE></ITEM>
      </BLIST></ITEM>
    </BLIST></ITEM>
    <ITEM><ANCHOR>RFC</ANCHOR><BLIST><TITLE>RFC</TITLE>
      <ITEM><ARTICLE><X><T>RFC 439</T><ST>PARRY Encounters the DOCTOR</ST><A>https://www.ietf.org/rfc/rfc439.txt</A><L>en</L><F>HTML</F></X><AUTHOR><FIRSTNAME>Vinton</FIRSTNAME><LASTNAME>Cerf</LASTNAME></AUTHOR><DATE><YEAR>1973</YEAR><MONTH>1</MONTH><DAY>21</DAY></DATE><COMMENT>Two computers discuss together.</COMMENT></ARTICLE></ITEM>
      <ITEM><ARTICLE><X><T>RFC 527</T><ST>ARPAWOCKY</ST><A>https://www.ietf.org/rfc/rfc527.txt</A><L>en</L><F>HTML</F></X><AUTHOR><FIRSTNAME>R.</FIRSTNAME><LASTNAME>Merryman</LASTNAME></AUTHOR><DATE><YEAR>1973</YEAR><MONTH>6</MONTH><DAY>22</DAY></DATE><COMMENT>Technical poesy.</COMMENT></ARTICLE></ITEM>
      <ITEM><ARTICLE><X><T>RFC 748</T><ST>Telnet Randomly-Lose Option</ST><A>https://www.ietf.org/rfc/rfc748.txt</A><L>en</L><F>HTML</F></X><AUTHOR><FIRSTNAME>Mark</FIRSTNAME><MIDDLENAME>R.</MIDDLENAME><LASTNAME>Crispin</LASTNAME></AUTHOR><DATE><YEAR>1978</YEAR><MONTH>4</MONTH><DAY>1</DAY></DATE><COMMENT>Disabling random data lossage.</COMMENT></ARTICLE></ITEM>
      <ITEM><ARTICLE><X><T>RFC 968</T><ST>Twas the Night Before Start-up</ST><A>https://www.ietf.org/rfc/rfc968.txt</A><L>en</L><F>HTML</F></X><AUTHOR><FIRSTNAME>Vinton</FIRSTNAME><LASTNAME>Cerf</LASTNAME></AUTHOR><DATE><YEAR>1985</YEAR><MONTH>12</MONTH></DATE><COMMENT>Yet another technical poem.</COMMENT></ARTICLE></ITEM>
      <ITEM><ARTICLE><X><T>RFC 1097</T><ST>TELNET SUBLIMINAL-MESSAGE Option</ST><A>https://www.ietf.org/rfc/rfc1097.txt</A><L>en</L><F>HTML</F></X><AUTHOR><FIRSTNAME>B.</FIRSTNAME><LASTNAME>Miller</LASTNAME></AUTHOR><DATE><YEAR>1989</YEAR><MONTH>4</MONTH><DAY>1</DAY></DATE><COMMENT>How to convince users to upgrade their Telnet version.</COMMENT></ARTICLE></ITEM>
      <ITEM><ARTICLE><X><T>RFC 1121</T><ST>Act One - The Poems</ST><A>https://www.ietf.org/rfc/rfc1121.txt</A><L>en</L><F>HTML</F></X><AUTHOR><FIRSTNAME>Jon</FIRSTNAME><LASTNAME>Postel</LASTNAME></AUTHOR><AUTHOR><FIRSTNAME>Leonard</FIRSTNAME><LASTNAME>Kleinrock</LASTNAME></AUTHOR><AUTHOR><FIRSTNAME>Vinton</FIRSTNAME><LASTNAME>Cerf</LASTNAME></AUTHOR><AUTHOR><FIRSTNAME>Barry</FIRSTNAME><LASTNAME>Boehm</LASTNAME></AUTHOR><DATE><YEAR>1989</YEAR><MONTH>9</MONTH></DATE><COMMENT>Some poetry.</COMMENT></ARTICLE></ITEM>
      <ITEM><ARTICLE><X><T>RFC 1149</T><ST>A Standard for the Transmission of IP Datagrams on Avian Carriers</ST><A>https://www.ietf.org/rfc/rfc1149.txt</A><L>en</L><F>HTML</F></X><AUTHOR><FIRSTNAME>D.</FIRSTNAME><LASTNAME>Waitzman</LASTNAME></AUTHOR><DATE><YEAR>1990</YEAR><MONTH>4</MONTH><DAY>1</DAY></DATE><COMMENT>Pigeon stuff.</COMMENT></ARTICLE></ITEM>
      <ITEM><ARTICLE><X><T>RFC 1216</T><ST>Gigabit Network Economics and Paradigm Shifts</ST><A>https://www.ietf.org/rfc/rfc1216.txt</A><L>en</L><F>HTML</F></X><AUTHOR><FIRSTNAME>Poorer</FIRSTNAME><LASTNAME>Richard</LASTNAME></AUTHOR><AUTHOR><GIVENNAME>Kynikos</GIVENNAME></AUTHOR><DATE><YEAR>1991</YEAR><MONTH>4</MONTH><DAY>1</DAY></DATE><COMMENT>The economy dictates slower networks.</COMMENT></ARTICLE></ITEM>
      <ITEM><ARTICLE><X><T>RFC 1217</T><ST>Memo from the Consortium for Slow Commotion Research (CSCR)</ST><A>https://www.ietf.org/rfc/rfc1217.txt</A><L>en</L><F>HTML</F></X><AUTHOR><FIRSTNAME>Vinton</FIRSTNAME><LASTNAME>Cerf</LASTNAME></AUTHOR><DATE><YEAR>1991</YEAR><MONTH>4</MONTH><DAY>1</DAY></DATE><COMMENT>Some possible implementations of <X><T>RFC 1216</T><A>https://www.ietf.org/rfc/rfc1216.txt</A><L>en</L><F>HTML</F></X>.</COMMENT></ARTICLE></ITEM>
      <ITEM><ARTICLE><X><T>RFC 1313</T><ST>Today's Programming for KRFC AM 1313 Internet Talk Radio</ST><A>https://www.ietf.org/rfc/rfc1313.txt</A><L>en</L><F>HTML</F></X><AUTHOR><FIRSTNAME>C.</FIRSTNAME><LASTNAME>Partridge</LASTNAME></AUTHOR><DATE><YEAR>1992</YEAR><MONTH>4</MONTH><DAY>1</DAY></DATE><COMMENT>A radiophonic private joke.</COMMENT></ARTICLE></ITEM>
      <ITEM><ARTICLE><X><T>RFC 1437</T><ST>The Extension of MIME Content-Types to a New Medium</ST><A>https://www.ietf.org/rfc/rfc1437.txt</A><L>en</L><F>HTML</F></X><AUTHOR><FIRSTNAME>N.</FIRSTNAME><LASTNAME>Borenstein</LASTNAME></AUTHOR><AUTHOR><FIRSTNAME>M.</FIRSTNAME><LASTNAME>Linimon</LASTNAME></AUTHOR><DATE><YEAR>1993</YEAR><MONTH>4</MONTH><DAY>1</DAY></DATE><COMMENT>Transporting politicians by email.</COMMENT></ARTICLE></ITEM>
      <ITEM><ARTICLE><X><T>RFC 1438</T><ST>Internet Engineering Task Force Statements Of Boredom (SOBs)</ST><A>https://www.ietf.org/rfc/rfc1438.txt</A><L>en</L><F>HTML</F></X><AUTHOR><FIRSTNAME>L.</FIRSTNAME><LASTNAME>Chapin</LASTNAME></AUTHOR><AUTHOR><FIRSTNAME>C.</FIRSTNAME><LASTNAME>Huitema</LASTNAME></AUTHOR><DATE><YEAR>1993</YEAR><MONTH>4</MONTH><DAY>1</DAY></DATE><COMMENT>Publishing important document containing no useful data.</COMMENT></ARTICLE></ITEM>
      <ITEM><ARTICLE><X><T>RFC 1605</T><ST>SONET to Sonnet Translation</ST><A>https://www.ietf.org/rfc/rfc1605.txt</A><L>en</L><F>HTML</F></X><AUTHOR><FIRSTNAME>C.</FIRSTNAME><LASTNAME>Marlow</LASTNAME></AUTHOR><AUTHOR><FIRSTNAME>R.</FIRSTNAME><LASTNAME>Bacon</LASTNAME></AUTHOR><AUTHOR><FIRSTNAME>C.</FIRSTNAME><LASTNAME>Partridge</LASTNAME></AUTHOR><DATE><YEAR>1994</YEAR><MONTH>4</MONTH><DAY>1</DAY></DATE><COMMENT>Poetic compression.</COMMENT></ARTICLE></ITEM>
      <ITEM><ARTICLE><X><T>RFC 1606</T><ST>A Historical Perspective On The Usage Of IP Version 9</ST><A>https://www.ietf.org/rfc/rfc1606.txt</A><L>en</L><F>HTML</F></X><AUTHOR><FIRSTNAME>Julian</FIRSTNAME><LASTNAME>Onions</LASTNAME></AUTHOR><DATE><YEAR>1994</YEAR><MONTH>4</MONTH><DAY>1</DAY></DATE><COMMENT>IP addresses for everything.</COMMENT></ARTICLE></ITEM>
      <ITEM><ARTICLE><X><T>RFC 1607</T><ST>A VIEW FROM THE 21ST CENTURY</ST><A>https://www.ietf.org/rfc/rfc1607.txt</A><L>en</L><F>HTML</F></X><AUTHOR><FIRSTNAME>Vinton</FIRSTNAME><LASTNAME>Cerf</LASTNAME></AUTHOR><DATE><YEAR>1994</YEAR><MONTH>4</MONTH><DAY>1</DAY></DATE><COMMENT>Back to the future.</COMMENT></ARTICLE></ITEM>
      <ITEM><ARTICLE><X><T>RFC 1776</T><ST>The Address is the Message</ST><A>https://www.ietf.org/rfc/rfc1776.txt</A><L>en</L><F>HTML</F></X><AUTHOR><FIRSTNAME>Steve</FIRSTNAME><LASTNAME>Crocker</LASTNAME></AUTHOR><DATE><YEAR>1995</YEAR><MONTH>4</MONTH><DAY>1</DAY></DATE><COMMENT>The content of this RFC is in its title.</COMMENT></ARTICLE></ITEM>
      <ITEM><ARTICLE><X><T>RFC 1882</T><ST>The 12-Days of Technology Before Christmas</ST><A>https://www.ietf.org/rfc/rfc1882.txt</A><L>en</L><F>HTML</F></X><AUTHOR><FIRSTNAME>Bill</FIRSTNAME><LASTNAME>Hancock</LASTNAME></AUTHOR><DATE><YEAR>1995</YEAR><MONTH>12</MONTH></DATE><COMMENT>A system administrator nightmare.</COMMENT></ARTICLE></ITEM>
      <ITEM><ARTICLE><X><T>RFC 1924</T><ST>A Compact Representation of IPv6 Addresses</ST><A>https://www.ietf.org/rfc/rfc1924.txt</A><L>en</L><F>HTML</F></X><AUTHOR><FIRSTNAME>Robert</FIRSTNAME><LASTNAME>Elz</LASTNAME></AUTHOR><DATE><YEAR>1996</YEAR><MONTH>4</MONTH><DAY>1</DAY></DATE><COMMENT>A serious study for a strange goal.</COMMENT></ARTICLE></ITEM>
      <ITEM><ARTICLE><X><T>RFC 1925</T><ST>The Twelve Networking Truths</ST><A>https://www.ietf.org/rfc/rfc1925.txt</A><L>en</L><F>HTML</F></X><AUTHOR><FIRSTNAME>Ross</FIRSTNAME><LASTNAME>Callon</LASTNAME></AUTHOR><DATE><YEAR>1996</YEAR><MONTH>4</MONTH><DAY>1</DAY></DATE><COMMENT>Corollary: cheap pigs cannot fly at light speed event if accessed via an indirection level.</COMMENT></ARTICLE></ITEM>
      <ITEM><ARTICLE><X><T>RFC 1926</T><ST>An Experimental Encapsulation of IP Datagrams on Top of ATM</ST><A>https://www.ietf.org/rfc/rfc1926.txt</A><L>en</L><F>HTML</F></X><AUTHOR><FIRSTNAME>Johnny</FIRSTNAME><LASTNAME>Eriksson</LASTNAME></AUTHOR><DATE><YEAR>1996</YEAR><MONTH>4</MONTH><DAY>1</DAY></DATE><COMMENT>Very short and not funny at all.</COMMENT></ARTICLE></ITEM>
      <ITEM><ARTICLE><X><T>RFC 1927</T><ST>Suggested Additional MIME Types for Associating Documents</ST><A>https://www.ietf.org/rfc/rfc1927.txt</A><L>en</L><F>HTML</F></X><AUTHOR><FIRSTNAME>Craig</FIRSTNAME><MIDDLENAME>Milo</MIDDLENAME><LASTNAME>Rogers</LASTNAME></AUTHOR><DATE><YEAR>1996</YEAR><MONTH>4</MONTH><DAY>1</DAY></DATE><COMMENT>Staple and papers clips…</COMMENT></ARTICLE></ITEM>
      <ITEM><ARTICLE><X><T>RFC 2100</T><ST>The Naming of Hosts</ST><A>https://www.ietf.org/rfc/rfc2100.txt</A><L>en</L><F>HTML</F></X><AUTHOR><FIRSTNAME>J.</FIRSTNAME><LASTNAME>Ashworth</LASTNAME></AUTHOR><DATE><YEAR>1997</YEAR><MONTH>4</MONTH><DAY>1</DAY></DATE><COMMENT>Each computer should have three different names.</COMMENT></ARTICLE></ITEM>
      <ITEM><ARTICLE><X><T>RFC 2321</T><ST>RITA -- The Reliable Internetwork Troubleshooting Agent</ST><A>https://www.ietf.org/rfc/rfc2321.txt</A><L>en</L><F>HTML</F></X><AUTHOR><FIRSTNAME>Andrew</FIRSTNAME><MIDDLENAME>K.</MIDDLENAME><LASTNAME>Bressen</LASTNAME></AUTHOR><DATE><YEAR>1998</YEAR><MONTH>4</MONTH><DAY>1</DAY></DATE><COMMENT>A new debugging tool. I am not sure of the species… maybe yet another pigeon.</COMMENT></ARTICLE></ITEM>
      <ITEM><ARTICLE><X><T>RFC 2322</T><ST>Management of IP numbers by peg-dhcp</ST><A>https://www.ietf.org/rfc/rfc2322.txt</A><L>en</L><F>HTML</F></X><AUTHOR><FIRSTNAME>Koos</FIRSTNAME><LASTNAME>van den Hout</LASTNAME></AUTHOR><AUTHOR><FIRSTNAME>Andre</FIRSTNAME><LASTNAME>Koopal</LASTNAME></AUTHOR><AUTHOR><FIRSTNAME>Remco</FIRSTNAME><LASTNAME>van Mook</LASTNAME></AUTHOR><DATE><YEAR>1998</YEAR><MONTH>4</MONTH><DAY>1</DAY></DATE><COMMENT>I know this is April’s Fool, but some companies could benefically apply this to avoid the usual mess when one guy declares his machine with the same IP address as his workmate.</COMMENT></ARTICLE></ITEM>
      <ITEM><ARTICLE><X><T>RFC 2323</T><ST>IETF Identification and Security Guidelines</ST><A>https://www.ietf.org/rfc/rfc2323.txt</A><L>en</L><F>HTML</F></X><AUTHOR><FIRSTNAME>Alegre</FIRSTNAME><LASTNAME>Ramos</LASTNAME></AUTHOR><DATE><YEAR>1998</YEAR><MONTH>4</MONTH><DAY>1</DAY></DATE><COMMENT>Beards are insecure.</COMMENT></ARTICLE></ITEM>
      <ITEM><ARTICLE><X><T>RFC 2324</T><ST>Hyper Text Coffee Pot Control Protocol (HTCPCP/1.0)</ST><A>https://www.ietf.org/rfc/rfc2324.txt</A><L>en</L><F>HTML</F></X><AUTHOR><FIRSTNAME>L.</FIRSTNAME><LASTNAME>Masinter</LASTNAME></AUTHOR><DATE><YEAR>1998</YEAR><MONTH>4</MONTH><DAY>1</DAY></DATE><COMMENT>I have no issue with not supporting decaffeinated brewing, but what’s the point of having raspberry syrup? American guys have no idea about what they are talking.</COMMENT></ARTICLE></ITEM>
      <ITEM><ARTICLE><X><T>RFC 2325</T><ST>Definitions of Managed Objects for Drip-Type Heated Beverage Hardware Devices using SMIv2</ST><A>https://www.ietf.org/rfc/rfc2325.txt</A><L>en</L><F>HTML</F></X><AUTHOR><FIRSTNAME>Michael</FIRSTNAME><LASTNAME>Slavitch</LASTNAME></AUTHOR><DATE><YEAR>1998</YEAR><MONTH>4</MONTH><DAY>1</DAY></DATE><COMMENT>An extension of <X><T>RFC1213</T><A>https://www.ietf.org/rfc/rfc1213.txt</A><L>en</L><F>HTML</F></X> for coffee machine (once again!).</COMMENT></ARTICLE></ITEM>
      <ITEM><ARTICLE><X><T>RFC 2549</T><ST>IP over Avian Carriers with Quality of Service</ST><A>https://www.ietf.org/rfc/rfc2549.txt</A><L>en</L><F>HTML</F></X><AUTHOR><FIRSTNAME>D.</FIRSTNAME><LASTNAME>Waitzman</LASTNAME></AUTHOR><DATE><YEAR>1999</YEAR><MONTH>4</MONTH><DAY>1</DAY></DATE><COMMENT>More pigeon stuff.</COMMENT></ARTICLE></ITEM>
      <ITEM><ARTICLE><X quality="1"><T>RFC 2550</T><ST>Y10K and Beyond</ST><A>https://www.ietf.org/rfc/rfc2550.txt</A><L>en</L><F>HTML</F></X><AUTHOR><FIRSTNAME>S.</FIRSTNAME><LASTNAME>Glassman</LASTNAME></AUTHOR><AUTHOR><FIRSTNAME>M.</FIRSTNAME><LASTNAME>Manasse</LASTNAME></AUTHOR><AUTHOR><FIRSTNAME>J.</FIRSTNAME><LASTNAME>Mogul</LASTNAME></AUTHOR><DATE><YEAR>1999</YEAR><MONTH>4</MONTH><DAY>1</DAY></DATE><COMMENT>A standard to avoid the Y10k and Y10**30 bugs.</COMMENT></ARTICLE></ITEM>
      <ITEM><ARTICLE><X><T>RFC 2551</T><ST>The Roman Standards Process -- Revision III</ST><A>https://www.ietf.org/rfc/rfc2551.txt</A><L>en</L><F>HTML</F></X><AUTHOR><FIRSTNAME>Scott</FIRSTNAME><LASTNAME>Bradner</LASTNAME></AUTHOR><DATE><YEAR>1999</YEAR><MONTH>4</MONTH><DAY>1</DAY></DATE><COMMENT>Not really a joke, but a slightly humorous description of the RFC process.</COMMENT></ARTICLE></ITEM>
      <ITEM><ARTICLE><X><T>RFC 2795</T><ST>The Infinite Monkey Protocol Suite (IMPS)</ST><A>https://www.ietf.org/rfc/rfc2795.txt</A><L>en</L><F>HTML</F></X><AUTHOR><FIRSTNAME>S.</FIRSTNAME><LASTNAME>Christey</LASTNAME></AUTHOR><DATE><YEAR>2000</YEAR><MONTH>4</MONTH><DAY>1</DAY></DATE><COMMENT>This draft describes a protocol to detect the recreation of Shakespeare’s work by an infinite number of monkeys.</COMMENT></ARTICLE></ITEM>
      <ITEM><ARTICLE><X><T>RFC 3091</T><ST>Pi Digit Generation Protocol</ST><A>https://www.ietf.org/rfc/rfc3091.txt</A><L>en</L><F>HTML</F></X><AUTHOR><FIRSTNAME>Hugh</FIRSTNAME><LASTNAME>Kennedy</LASTNAME></AUTHOR><DATE><YEAR>2001</YEAR><MONTH>4</MONTH><DAY>1</DAY></DATE><COMMENT>How to provide Pi digits.</COMMENT></ARTICLE></ITEM>
      <ITEM><ARTICLE><X><T>RFC 3092</T><ST>Etymology of "Foo"</ST><A>https://www.ietf.org/rfc/rfc3092.txt</A><L>en</L><F>HTML</F></X><AUTHOR><FIRSTNAME>Donald</FIRSTNAME><MIDDLENAME>E.</MIDDLENAME><LASTNAME>Eastlake</LASTNAME></AUTHOR><AUTHOR><FIRSTNAME>Carl-Uno</FIRSTNAME><LASTNAME>Manros</LASTNAME></AUTHOR><AUTHOR><FIRSTNAME>Eric</FIRSTNAME><MIDDLENAME>S.</MIDDLENAME><LASTNAME>Raymond</LASTNAME></AUTHOR><DATE><YEAR>2001</YEAR><MONTH>4</MONTH><DAY>1</DAY></DATE><COMMENT>Not a joke but the etymology of foo, bar and foobar.</COMMENT></ARTICLE></ITEM>
      <ITEM><ARTICLE><X><T>RFC 3093</T><ST>Firewall Enhancement Protocol (FEP)</ST><A>https://www.ietf.org/rfc/rfc3093.txt</A><L>en</L><F>HTML</F></X><AUTHOR><FIRSTNAME>Mark</FIRSTNAME><LASTNAME>Gaynor</LASTNAME></AUTHOR><AUTHOR><FIRSTNAME>Scott</FIRSTNAME><LASTNAME>Bradner</LASTNAME></AUTHOR><DATE><YEAR>2001</YEAR><MONTH>4</MONTH><DAY>1</DAY></DATE><COMMENT>Tunneling through firewalls by transmitting TCP/UDP over HTTP.</COMMENT></ARTICLE></ITEM>
      <ITEM><ARTICLE><X><T>RFC 3251</T><ST>Electricity over IP</ST><A>https://www.ietf.org/rfc/rfc3251.txt</A><L>en</L><F>HTML</F></X><AUTHOR><FIRSTNAME>Bala</FIRSTNAME><LASTNAME>Rajagopalan</LASTNAME></AUTHOR><DATE><YEAR>2002</YEAR><MONTH>4</MONTH><DAY>1</DAY></DATE><COMMENT>The title says it all.</COMMENT></ARTICLE></ITEM>
      <ITEM><ARTICLE><X><T>RFC 3252</T><ST>Binary Lexical Octet Ad-hoc Transport</ST><A>https://www.ietf.org/rfc/rfc3252.txt</A><L>en</L><F>HTML</F></X><AUTHOR><FIRSTNAME>Hugh</FIRSTNAME><LASTNAME>Kennedy</LASTNAME></AUTHOR><DATE><YEAR>2002</YEAR><MONTH>4</MONTH><DAY>1</DAY></DATE><COMMENT>Implement IP, TCP and UDP as XML.</COMMENT></ARTICLE></ITEM>
      <ITEM><ARTICLE><X><T>RFC 3751</T><ST>Omniscience Protocol Requirements</ST><A>https://www.ietf.org/rfc/rfc3751.txt</A><L>en</L><F>HTML</F></X><AUTHOR><FIRSTNAME>Scott</FIRSTNAME><LASTNAME>Bradner</LASTNAME></AUTHOR><DATE><YEAR>2004</YEAR><MONTH>4</MONTH><DAY>1</DAY></DATE><COMMENT>A protocol to tag out protected material on every computer. May be slightly difficult to implement…</COMMENT></ARTICLE></ITEM>
      <ITEM><ARTICLE><X><T>RFC 4041</T><ST>Requirements for Morality Sections in Routing Area Drafts</ST><A>https://www.ietf.org/rfc/rfc4041.txt</A><L>en</L><F>HTML</F></X><AUTHOR><FIRSTNAME>Adrian</FIRSTNAME><LASTNAME>Farrel</LASTNAME></AUTHOR><DATE><YEAR>2005</YEAR><MONTH>4</MONTH><DAY>1</DAY></DATE><COMMENT>Introducing morality in Internet standards.</COMMENT></ARTICLE></ITEM>
      <ITEM><ARTICLE><X><T>RFC 4042</T><ST>UTF-9 and UTF-18 Efficient Transformation Formats of Unicode</ST><A>https://www.ietf.org/rfc/rfc4042.txt</A><L>en</L><F>HTML</F></X><AUTHOR><FIRSTNAME>Mark</FIRSTNAME><MIDDLENAME>R.</MIDDLENAME><LASTNAME>Crispin</LASTNAME></AUTHOR><DATE><YEAR>2005</YEAR><MONTH>4</MONTH><DAY>1</DAY></DATE><COMMENT>Supporting UNICODE on nonet architectures.</COMMENT></ARTICLE></ITEM>
      <ITEM><ARTICLE><X><T>RFC 4824</T><ST>The Transmission of IP Datagrams over the Semaphore Flag Signaling System (SFSS)</ST><A>https://www.ietf.org/rfc/rfc4824.txt</A><L>en</L><F>HTML</F></X><AUTHOR><FIRSTNAME>J.</FIRSTNAME><LASTNAME>Hofmueller</LASTNAME></AUTHOR><AUTHOR><FIRSTNAME>IO.</FIRSTNAME><LASTNAME>zmoelnig</LASTNAME></AUTHOR><AUTHOR><FIRSTNAME>A.</FIRSTNAME><LASTNAME>Bachmann</LASTNAME></AUTHOR><DATE><YEAR>2007</YEAR><MONTH>4</MONTH><DAY>1</DAY></DATE><COMMENT>Transmiting IP over Chappe’s invention.</COMMENT></ARTICLE></ITEM>
      <ITEM><ARTICLE><X><T>RFC 7168</T><ST>The Hyper Text Coffee Pot Control Protocol for Tea Efflux Appliances (HTCPCP-TEA)</ST><A>https://www.ietf.org/rfc/rfc7168.txt</A><L>en</L><F>HTML</F></X><AUTHOR><FIRSTNAME>Imran</FIRSTNAME><LASTNAME>Nazar</LASTNAME></AUTHOR><DATE><YEAR>2014</YEAR><MONTH>4</MONTH><DAY>1</DAY></DATE><COMMENT>An extension of Hyper Text Coffee Pot Control Protocol for tea.</COMMENT></ARTICLE></ITEM>
      <ITEM><ARTICLE><X><T>RFC 7169</T><ST>The NSA (No Secrecy Afforded) Certificate Extension</ST><A>https://www.ietf.org/rfc/rfc7169.txt</A><L>en</L><F>HTML</F></X><AUTHOR><FIRSTNAME>Sean</FIRSTNAME><LASTNAME>Turner</LASTNAME></AUTHOR><DATE><YEAR>2014</YEAR><MONTH>4</MONTH><DAY>1</DAY></DATE><COMMENT>Declaring either that the key has been shared or that you cannot indicate that the key been shared.</COMMENT></ARTICLE></ITEM>
    </BLIST></ITEM>
    <ITEM><BLIST><TITLE>Stan Kelly-Bootle</TITLE>
      <ITEM><ARTICLE><X><T>Devil's Advocate: Sigh No More for the Time Being</T><A>https://www.drdobbs.com/devils-advocate-sigh-no-more-for-the-tim/199103050</A><L>en</L><F>HTML</F></X><AUTHOR><FIRSTNAME>Stan</FIRSTNAME><LASTNAME>Kelly-Bootle</LASTNAME></AUTHOR><DATE><YEAR>2000</YEAR><MONTH>1</MONTH></DATE><COMMENT>First Y2K, then Stan’s mathematical studies…</COMMENT></ARTICLE></ITEM>
      <ITEM><ARTICLE><X status="dead"><T>Webbing On</T><A>http://www.unixreview.com/documents/s=1251/urm0001da/</A><L>en</L><F>HTML</F></X><AUTHOR><FIRSTNAME>Stan</FIRSTNAME><LASTNAME>Kelly-Bootle</LASTNAME></AUTHOR><DATE><YEAR>2000</YEAR><MONTH>1</MONTH></DATE><COMMENT>Marketing words.</COMMENT></ARTICLE></ITEM>
      <ITEM><ARTICLE><X status="dead"><T>Back at the Saddle Point Again</T><A>http://www.performancecomputing.com/columns/stan/stans031500.shtml</A><L>en</L><F>HTML</F></X><AUTHOR><FIRSTNAME>Stan</FIRSTNAME><LASTNAME>Kelly-Bootle</LASTNAME></AUTHOR><DATE><YEAR>2000</YEAR><MONTH>3</MONTH><DAY>15</DAY></DATE><COMMENT>Paper mags, funerals and Windows 2000 source code.</COMMENT></ARTICLE></ITEM>
      <ITEM><ARTICLE><X status="dead"><T>Even so</T><A>http://www.performancecomputing.com/columns/stan/stans042000.shtml</A><L>en</L><F>HTML</F></X><AUTHOR><FIRSTNAME>Stan</FIRSTNAME><LASTNAME>Kelly-Bootle</LASTNAME></AUTHOR><DATE><YEAR>2000</YEAR><MONTH>4</MONTH><DAY>20</DAY></DATE><COMMENT>Four letters words and phaticism.</COMMENT></ARTICLE></ITEM>
      <ITEM><ARTICLE><X status="dead"><T>The Comics Creed</T><A>http://www.performancecomputing.com/columns/stan/stans052400.shtml</A><L>en</L><F>HTML</F></X><AUTHOR><FIRSTNAME>Stan</FIRSTNAME><LASTNAME>Kelly-Bootle</LASTNAME></AUTHOR><DATE><YEAR>2000</YEAR><MONTH>5</MONTH><DAY>24</DAY></DATE><COMMENT>Puns and logical tests for the voters.</COMMENT></ARTICLE></ITEM>
      <ITEM><ARTICLE><X status="dead"><T>Meat and Other Spaces</T><A>http://www.performancecomputing.com/columns/stan/stans062900.shtml</A><L>en</L><F>HTML</F></X><AUTHOR><FIRSTNAME>Stan</FIRSTNAME><LASTNAME>Kelly-Bootle</LASTNAME></AUTHOR><DATE><YEAR>2000</YEAR><MONTH>6</MONTH><DAY>29</DAY></DATE><COMMENT>The art of hunting the first citation of a word.</COMMENT></ARTICLE></ITEM>
      <ITEM><ARTICLE><X status="dead"><T>Mind The Gap!</T><A>http://www.performancecomputing.com/columns/stan/stans073100.shtml</A><L>en</L><F>HTML</F></X><AUTHOR><FIRSTNAME>Stan</FIRSTNAME><LASTNAME>Kelly-Bootle</LASTNAME></AUTHOR><DATE><YEAR>2000</YEAR><MONTH>7</MONTH><DAY>31</DAY></DATE><COMMENT>From the London tube to the Digital Divide.</COMMENT></ARTICLE></ITEM>
      <ITEM><ARTICLE><X status="dead"><T>Figured Speech</T><A>http://www.performancecomputing.com/columns/stan/stans091200.shtml</A><L>en</L><F>HTML</F></X><AUTHOR><FIRSTNAME>Stan</FIRSTNAME><LASTNAME>Kelly-Bootle</LASTNAME></AUTHOR><DATE><YEAR>2000</YEAR><MONTH>9</MONTH><DAY>12</DAY></DATE><COMMENT>About some figures of speech and C++ at FermiLab.</COMMENT></ARTICLE></ITEM>
      <ITEM><ARTICLE><X status="dead"><T>Redux Redux</T><A>http://www.performancecomputing.com/columns/stan/stans101700.shtml</A><L>en</L><F>HTML</F></X><AUTHOR><FIRSTNAME>Stan</FIRSTNAME><LASTNAME>Kelly-Bootle</LASTNAME></AUTHOR><DATE><YEAR>2000</YEAR><MONTH>10</MONTH><DAY>17</DAY></DATE><COMMENT>OS/language definition and the black crow paradox.</COMMENT></ARTICLE></ITEM>
      <ITEM><ARTICLE><X status="dead"><T>New Words For Old</T><A>http://www.performancecomputing.com/columns/stan/stans112800.shtml</A><L>en</L><F>HTML</F></X><AUTHOR><FIRSTNAME>Stan</FIRSTNAME><LASTNAME>Kelly-Bootle</LASTNAME></AUTHOR><DATE><YEAR>2000</YEAR><MONTH>11</MONTH><DAY>29</DAY></DATE><COMMENT>US elections and chaos theory.</COMMENT></ARTICLE></ITEM>
      <ITEM><ARTICLE><X status="dead"><T>The Watchman On The Firewall</T><A>http://www.performancecomputing.com/columns/stan/stans031401.shtml</A><L>en</L><F>HTML</F></X><AUTHOR><FIRSTNAME>Stan</FIRSTNAME><LASTNAME>Kelly-Bootle</LASTNAME></AUTHOR><DATE><YEAR>2001</YEAR><MONTH>3</MONTH><DAY>14</DAY></DATE><COMMENT>Trojan devil.</COMMENT></ARTICLE></ITEM>
    </BLIST></ITEM>
    <ITEM><BLIST><TITLE>Mike Swaine</TITLE>
      <ITEM><ARTICLE><X status="dead"><T>UNIX, UNIXReview, and You</T><A>http://www.unixreview.com/archives/articles/2000/march/swaine032000.shtml</A><L>en</L><F>HTML</F></X><AUTHOR><FIRSTNAME>Mike</FIRSTNAME><LASTNAME>Swaine</LASTNAME></AUTHOR><DATE><YEAR>2000</YEAR><MONTH>3</MONTH></DATE><COMMENT>The rebirth of UNIXReview is fueled by the Linux success.</COMMENT></ARTICLE></ITEM>
      <ITEM><ARTICLE><X status="dead"><T>It's a Unix Portal! (Cool!)</T><A>http://www.unixreview.com/archives/articles/2000/april/swaine041700.shtml</A><L>en</L><F>HTML</F></X><AUTHOR><FIRSTNAME>Mike</FIRSTNAME><LASTNAME>Swaine</LASTNAME></AUTHOR><DATE><YEAR>2000</YEAR><MONTH>4</MONTH></DATE><COMMENT>Lowercasing and leaning right.</COMMENT></ARTICLE></ITEM>
      <ITEM><ARTICLE><X status="dead"><T>A Cynic’s Good Year</T><A>http://www.unixreview.com/archives/articles/2000/may/swaine051000.shtml</A><L>en</L><F>HTML</F></X><AUTHOR><FIRSTNAME>Mike</FIRSTNAME><LASTNAME>Swaine</LASTNAME></AUTHOR><DATE><YEAR>2000</YEAR><MONTH>5</MONTH></DATE><COMMENT>Unix on desktop, backup poetry and Unix Review columnists.</COMMENT></ARTICLE></ITEM>
      <ITEM><ARTICLE><X status="dead"><T>Begging to Differ</T><A>http://www.unixreview.com/archives/articles/2000/june/swaine061300.shtml</A><L>en</L><F>HTML</F></X><AUTHOR><FIRSTNAME>Mike</FIRSTNAME><LASTNAME>Swaine</LASTNAME></AUTHOR><DATE><YEAR>2000</YEAR><MONTH>6</MONTH><DAY>13</DAY></DATE><COMMENT>Open source, <AUTHOR><FIRSTNAME>Bertrand</FIRSTNAME><LASTNAME>Meyer</LASTNAME></AUTHOR> and the editorial name.</COMMENT></ARTICLE></ITEM>
      <ITEM><ARTICLE><X status="dead"><T>Being unixreview</T><A>http://www.unixreview.com/archives/articles/2000/july/swaine071700.shtml</A><L>en</L><F>HTML</F></X><AUTHOR><FIRSTNAME>Mike</FIRSTNAME><LASTNAME>Swaine</LASTNAME></AUTHOR><DATE><YEAR>2000</YEAR><MONTH>7</MONTH><DAY>17</DAY></DATE><COMMENT>Deep link, virtual press office and amateur journalism.</COMMENT></ARTICLE></ITEM>
      <ITEM><ARTICLE><X status="dead"><T>The Cult of Personality</T><A>http://www.unixreview.com/archives/articles/2000/august/swaine081500.shtml</A><L>en</L><F>HTML</F></X><AUTHOR><FIRSTNAME>Mike</FIRSTNAME><LASTNAME>Swaine</LASTNAME></AUTHOR><DATE><YEAR>2000</YEAR><MONTH>8</MONTH><DAY>16</DAY></DATE><COMMENT>Synecdoche, Unix heroes, and UI cartoons.</COMMENT></ARTICLE></ITEM>
    </BLIST></ITEM>
  </BLIST></ITEM>
</LLIST>
</CONTENT>
</PAGE>