<?xml version="1.0"?>
<?xml-stylesheet type="text/xsl" href="../css/strict.xsl"?>
<PAGE xmlns:xsi="http://www.w3.org/2001/XMLSchema-instance" xsi:noNamespaceSchemaLocation="../css/schema.xsd" xml:lang="en">
<TITLE>FDA</TITLE>
<PATH>notes/fda.xml</PATH>
<DATE><YEAR>2010</YEAR><MONTH>10</MONTH><DAY>25</DAY></DATE>
<CONTENT>
<U><B>Design History File</B></U> (DHF) - Fichier Historique de Conception<BR/>
compilation of records which describes the design history of a finished device.<BR/>
<BR/>
<U><B>Device History Record</B></U> (DHR) - Dossier Historique du Dispositif<BR/>
compilation of records containing the production history of a finished device. <BR/>
<BR/>
<U><B>Device Master Record</B></U> (DMR) - Dossier Principal du Dispositif<BR/>
compilation of records containing the procedures and specifications for a finished device.<BR/>
<BR/>
<U><B>Medical Device Reporting</B></U> (MDR) - Rapports sur les instruments et dispositifs médicaux<BR/>
<X><T>https://www.fda.gov/MedicalDevices/Safety/ReportaProblem/default.htm</T><A>https://www.fda.gov/MedicalDevices/Safety/ReportaProblem/default.htm</A><L>en</L><F>HTML</F></X><BR/>
specified by 21 CFR part 803<BR/>
MDR is the mechanism for the FDA to receive significant medical device adverse events from manufacturers, importers and user facilities, so they can be detected and corrected quickly<BR/>
</CONTENT>
<X><T>links</T><A>../links/medical.html#FDA</A><L>en</L><F>HTML</F></X>
</PAGE>