<?xml version="1.0"?>
<?xml-stylesheet type="text/xsl" href="../css/strict.xsl"?>
<PAGE xmlns:xsi="http://www.w3.org/2001/XMLSchema-instance" xsi:noNamespaceSchemaLocation="../css/schema.xsd" xml:lang="en">
<TITLE>Unit Testing</TITLE>
<PATH>notes/unittest.xml</PATH>
<DATE><YEAR>2020</YEAR><MONTH>3</MONTH><DAY>7</DAY></DATE>
<CONTENT>
<BLIST><TITLE><B>Three steps</B> (see <X><T>here</T><A>https://xp123.com/articles/3a-arrange-act-assert/</A><L>en</L><F>HTML</F></X>)</TITLE>
<ITEM>Arrange</ITEM>
<ITEM>Act</ITEM>
<ITEM>Assert</ITEM>
</BLIST>
<BLIST><TITLE>xUnit rather uses <B>Four-Phase Test</B> (see <X><T>here</T><A>http://xunitpatterns.com/Four%20Phase%20Test.html</A><L>en</L><F>HTML</F></X>)</TITLE>
<ITEM>Setup</ITEM>
<ITEM>Exercise</ITEM>
<ITEM>Verify</ITEM>
<ITEM>Teardown</ITEM>
</BLIST>
<BLIST><TITLE>Compare with BDD's <B>GWT</B> (see <X><T>here</T><A>https://martinfowler.com/bliki/GivenWhenThen.html</A><L>en</L><F>HTML</F></X>)</TITLE>
<ITEM>Given</ITEM>
<ITEM>When</ITEM>
<ITEM>Then</ITEM>
</BLIST>
<B>Naming convention</B><BR/>
MethodName_StateUnderTest_ExpectedBehavior
</CONTENT>
<X><T>links</T><A>../links/autotest.html</A><L>en</L><F>HTML</F></X>
</PAGE>